pulumi_argocd/__init__.py
pulumi_argocd/_inputs.py
pulumi_argocd/_utilities.py
pulumi_argocd/account_token.py
pulumi_argocd/application.py
pulumi_argocd/application_set.py
pulumi_argocd/cluster.py
pulumi_argocd/outputs.py
pulumi_argocd/project.py
pulumi_argocd/project_token.py
pulumi_argocd/provider.py
pulumi_argocd/pulumi-plugin.json
pulumi_argocd/py.typed
pulumi_argocd/repository.py
pulumi_argocd/repository_certificate.py
pulumi_argocd/repository_credentials.py
pulumi_argocd/config/__init__.py
pulumi_argocd/config/__init__.pyi
pulumi_argocd/config/outputs.py
pulumi_argocd/config/vars.py
pulumi_argocd-1.0.1.dist-info/METADATA
pulumi_argocd-1.0.1.dist-info/WHEEL
pulumi_argocd-1.0.1.dist-info/top_level.txt
pulumi_argocd-1.0.1.dist-info/RECORD
